categorical_gpt/__init__.py
categorical_gpt/api.py
categorical_gpt/cgpt.py
categorical_gpt/coloring.py
categorical_gpt/embedding.py
categorical_gpt/llm_driver.py
categorical_gpt/ordering.py
categorical_gpt/gui/.output/public/200.html
categorical_gpt/gui/.output/public/404.html
categorical_gpt/gui/.output/public/favicon.ico
categorical_gpt/gui/.output/public/index.html
categorical_gpt/gui/.output/public/_nuxt/CharacteristicList.vue.6c83e2e5.js
categorical_gpt/gui/.output/public/_nuxt/Icon.6f5d80f8.css
categorical_gpt/gui/.output/public/_nuxt/Icon.b886924b.js
categorical_gpt/gui/.output/public/_nuxt/IconCSS.d58c1c07.js
categorical_gpt/gui/.output/public/_nuxt/IconCSS.fe0874d9.css
categorical_gpt/gui/.output/public/_nuxt/characteristics.d93be32d.js
categorical_gpt/gui/.output/public/_nuxt/config.7089e39b.js
categorical_gpt/gui/.output/public/_nuxt/default.a46e7375.js
categorical_gpt/gui/.output/public/_nuxt/entry.b3bec99e.css
categorical_gpt/gui/.output/public/_nuxt/entry.db242d8d.js
categorical_gpt/gui/.output/public/_nuxt/error-404.95c28eb4.css
categorical_gpt/gui/.output/public/_nuxt/error-404.b8bbac06.js
categorical_gpt/gui/.output/public/_nuxt/error-500.e2db7568.js
categorical_gpt/gui/.output/public/_nuxt/error-500.e798523c.css
categorical_gpt/gui/.output/public/_nuxt/export.b539cb84.js
categorical_gpt/gui/.output/public/_nuxt/index.e20e581f.js
categorical_gpt/gui/.output/public/_nuxt/results.aac670f9.js
categorical_gpt/gui/.output/public/_nuxt/value-assignments.c4e47c48.js
categorical_gpt/gui/.output/public/_nuxt/wizzard.b3d15bb3.js
categorical_gpt/gui/.output/public/characteristics/index.html
categorical_gpt/gui/.output/public/export/index.html
categorical_gpt/gui/.output/public/results/index.html
categorical_gpt/gui/.output/public/value-assignments/index.html
categorical_gpt-0.1.12.dist-info/LICENSE.txt
categorical_gpt-0.1.12.dist-info/METADATA
categorical_gpt-0.1.12.dist-info/WHEEL
categorical_gpt-0.1.12.dist-info/top_level.txt
categorical_gpt-0.1.12.dist-info/RECORD
