Metadata-Version: 2.1
Name: categorical-gpt
Version: 0.1.12
Summary: Transformation of categorical data to numerical feature vectors with Large Language Models
Home-page: https://github.com/khuesmann/categorical-gpt
Author: Karim Huesmann
Author-email: karimhuesmann@gmail.com
Project-URL: Homepage, https://github.com/khuesmann/categorical-gpt
Project-URL: Bug Tracker, https://github.com/khuesmann/categorical-gpt/issues
Classifier: Programming Language :: Python :: 3
Classifier: License :: OSI Approved :: MIT License
Classifier: Operating System :: OS Independent
Requires-Python: >=3.6
License-File: LICENSE.txt
Requires-Dist: scikit-learn
Requires-Dist: scikit-image
Requires-Dist: numpy
Requires-Dist: flask
Requires-Dist: flask-cors
Requires-Dist: networkx
Requires-Dist: umap-learn
Requires-Dist: loguru
Requires-Dist: requests
Requires-Dist: llm
